wordcloud/__init__.py
wordcloud/__main__.py
wordcloud/_version.py
wordcloud/color_from_image.py
wordcloud/query_integral_image.cpython-311-darwin.so
wordcloud/tokenization.py
wordcloud/wordcloud.py
wordcloud/wordcloud_cli.py
wordcloudKr-0.0.2.dist-info/LICENSE
wordcloudKr-0.0.2.dist-info/METADATA
wordcloudKr-0.0.2.dist-info/WHEEL
wordcloudKr-0.0.2.dist-info/entry_points.txt
wordcloudKr-0.0.2.dist-info/top_level.txt
wordcloudKr-0.0.2.dist-info/RECORD
