Metadata-Version: 2.1
Name: wordcloudKr
Version: 0.0.2
Summary: A little word cloud generator
Author-email: Andreas Mueller <t3kcit+wordcloud@gmail.com>
License: MIT License
Project-URL: Homepage, https://github.com/111coding/word_cloud
Requires-Python: >=3.7
License-File: LICENSE
Requires-Dist: numpy >=1.6.1
Requires-Dist: pillow
Requires-Dist: matplotlib
